mountetna/__init__.py
mountetna/auth.py
mountetna/etna.py
mountetna/etna_base.py
mountetna/gnomon.py
mountetna/janus.py
mountetna/magma.py
mountetna/metis.py
mountetna/polyphemus.py
mountetna/tests/__init__.py
mountetna/tests/conftest.py
mountetna/tests/test_janus.py
mountetna/tests/test_magma.py
mountetna/tests/test_metis.py
mountetna/tests/test_polyphemus.py
mountetna/utils/__init__.py
mountetna/utils/gater.py
mountetna/utils/inject.py
mountetna/utils/iterables.py
mountetna/utils/multipart.py
mountetna/utils/parser.py
mountetna/utils/streaming.py
mountetna-0.1.6.dist-info/METADATA
mountetna-0.1.6.dist-info/WHEEL
mountetna-0.1.6.dist-info/RECORD
