Metadata-Version: 2.1
Name: mountetna
Version: 0.1.6
Summary: Client package for Mount Etna data library
Home-page: https://github.com/mountetna/monoetna
License: GPL-2.0-only
Keywords: mount etna,data library
Author: Zachary Collins
Author-email: zachary.collins@ucsf.edu
Requires-Python: >=3.8,<4.0
Classifier: License :: OSI Approved :: GNU General Public License v2 (GPLv2)
Classifier: Programming Language :: Python :: 3
Classifier: Programming Language :: Python :: 3.8
Classifier: Programming Language :: Python :: 3.9
Classifier: Programming Language :: Python :: 3.10
Classifier: Programming Language :: Python :: 3.11
Requires-Dist: cryptography (>=37.0.3,<38.0.0)
Requires-Dist: pandas (>=1.2.1,<2.0.0)
Requires-Dist: pyserde (>=0.8.2,<0.9.0)
Requires-Dist: requests (>=2.28.0,<3.0.0)
Project-URL: Repository, https://github.com/mountetna/monoetna/
